minichain/__init__.py
minichain/chains.py
minichain/rag_runner.py
minichain/chat_models/__init__.py
minichain/chat_models/azure.py
minichain/chat_models/base.py
minichain/chat_models/local.py
minichain/chat_models/openrouter.py
minichain/chat_models/run.py
minichain/core/__init__.py
minichain/core/types.py
minichain/core/utils.py
minichain/embeddings/__init__.py
minichain/embeddings/azure.py
minichain/embeddings/base.py
minichain/embeddings/local.py
minichain/embeddings/openai.py
minichain/output_parsers/__init__.py
minichain/output_parsers/base.py
minichain/output_parsers/json_parser.py
minichain/output_parsers/pydantic_parser.py
minichain/prompts/__init__.py
minichain/prompts/base.py
minichain/prompts/chat.py
minichain/prompts/few_shot.py
minichain/prompts/prompt_template.py
minichain/text_splitters/__init__.py
minichain/utils/__init__.py
minichain/utils/json_utils.py
minichain/vectors/__init__.py
minichain/vectors/azure_ai_search.py
minichain/vectors/base.py
minichain/vectors/faiss.py
minichain_ai-8.0.5.dist-info/licenses/LICENSE
minichain_ai-8.0.5.dist-info/METADATA
minichain_ai-8.0.5.dist-info/WHEEL
minichain_ai-8.0.5.dist-info/top_level.txt
minichain_ai-8.0.5.dist-info/RECORD
