Metadata-Version: 2.4
Name: minichain-ai
Version: 8.0.5
Summary: A micro-framework for building with LLMs, inspired by LangChain.
Author-email: Fady <contact@fadymohamed.com>
License: MIT License
Project-URL: Homepage, https://github.com/fady17/minichain
Project-URL: Issues, https://github.com/fady17/minichain/issues
Requires-Python: >=3.9
License-File: LICENSE
Requires-Dist: pydantic>=2.0
Requires-Dist: jinja2>=3.0
Requires-Dist: openai>=1.0
Requires-Dist: python-dotenv
Requires-Dist: langchain-text-splitters
Provides-Extra: local
Requires-Dist: faiss-cpu<1.12,>=1.7.4; extra == "local"
Requires-Dist: numpy<2.0,>=1.22; extra == "local"
Provides-Extra: gpu
Requires-Dist: faiss-gpu<1.12,>=1.7.4; extra == "gpu"
Requires-Dist: numpy<2.0,>=1.22; extra == "gpu"
Provides-Extra: azure
Requires-Dist: azure-search-documents; extra == "azure"
Requires-Dist: azure-core; extra == "azure"
Provides-Extra: all
Requires-Dist: minichain-ai[local]; extra == "all"
Requires-Dist: minichain-ai[azure]; extra == "all"
Dynamic: license-file
